AUTHORS.rst
CHANGELOG.txt
MANIFEST.in
README.rst
setup.cfg
setup.py
coa_wagtail_modeltranslation.egg-info/PKG-INFO
coa_wagtail_modeltranslation.egg-info/SOURCES.txt
coa_wagtail_modeltranslation.egg-info/dependency_links.txt
coa_wagtail_modeltranslation.egg-info/requires.txt
coa_wagtail_modeltranslation.egg-info/top_level.txt
docs/AUTHORS.rst
docs/CHANGELOG.rst
docs/Installation.rst
docs/Introduction.rst
docs/Registering Models.rst
docs/advanced settings.rst
docs/caveats.rst
docs/index.rst
docs/management commands.rst
docs/recommended reading.rst
docs/template tags.rst
docs/releases/0.6.0.rst
docs/releases/index.rst
wagtail_modeltranslation/__init__.py
wagtail_modeltranslation/apps.py
wagtail_modeltranslation/contextlib.py
wagtail_modeltranslation/patch_wagtailadmin.py
wagtail_modeltranslation/patch_wagtailadmin_forms.py
wagtail_modeltranslation/settings.py
wagtail_modeltranslation/translation.py
wagtail_modeltranslation/utils.py
wagtail_modeltranslation/wagtail_hooks.py
wagtail_modeltranslation/makemigrations/__init__.py
wagtail_modeltranslation/makemigrations/apps.py
wagtail_modeltranslation/makemigrations/management/__init__.py
wagtail_modeltranslation/makemigrations/management/commands/__init__.py
wagtail_modeltranslation/makemigrations/management/commands/makemigrations.py
wagtail_modeltranslation/makemigrations/management/commands/makemigrations_original.py
wagtail_modeltranslation/management/__init__.py
wagtail_modeltranslation/management/commands/__init__.py
wagtail_modeltranslation/management/commands/makemigrations_translation.py
wagtail_modeltranslation/management/commands/migrate_translation.py
wagtail_modeltranslation/management/commands/set_translation_url_paths.py
wagtail_modeltranslation/management/commands/sync_page_translation_fields.py
wagtail_modeltranslation/management/commands/update_translation_fields.py
wagtail_modeltranslation/migrate/__init__.py
wagtail_modeltranslation/migrate/apps.py
wagtail_modeltranslation/migrate/management/__init__.py
wagtail_modeltranslation/migrate/management/commands/__init__.py
wagtail_modeltranslation/migrate/management/commands/migrate.py
wagtail_modeltranslation/migrate/management/commands/migrate_original.py
