Metadata-Version: 1.2
Name: coa-wagtail-modeltranslation
Version: 0.10.6
Summary: Translates Wagtail CMS models using a registration approach.
Home-page: https://github.com/infoportugal/wagtail-modeltranslation
Author: InfoPortugal, S.A.
Author-email: ericandrewsherman@gmail.com
Maintainer: InfoPortugal, S.A.
Maintainer-email: ericandrewsherman@gmail.com
License: New BSD
Platform: UNKNOWN
Classifier: Programming Language :: Python
Classifier: Programming Language :: Python :: 2.7
Classifier: Programming Language :: Python :: 3
Classifier: Programming Language :: Python :: 3.4
Classifier: Programming Language :: Python :: 3.5
Classifier: Programming Language :: Python :: 3.6
Classifier: Programming Language :: Python :: 3.7
Classifier: Operating System :: OS Independent
Classifier: Environment :: Web Environment
Classifier: Intended Audience :: Developers
Classifier: Framework :: Django
Classifier: License :: OSI Approved :: BSD License
